[
    {
        "name": "id",
        "dbType": "bigInteger,true,true",
        "htmlType": null,
        "validations": null,
        "searchable": false,
        "fillable": false,
        "primary": true,
        "inForm": false,
        "inIndex": false,
        "inView": false
    },
    {
        "name": "name",
        "dbType": "string,255",
        "htmlType": "text",
        "validations": "required|string|max:255|string|max:255|string|max:255",
        "searchable": true,
        "fillable": true,
        "primary": false,
        "inForm": true,
        "inIndex": true,
        "inView": true
    },
    {
        "name": "email",
        "dbType": "string,255",
        "htmlType": "text",
        "validations": "required|string|max:255|string|max:255|string|max:255",
        "searchable": true,
        "fillable": true,
        "primary": false,
        "inForm": true,
        "inIndex": true,
        "inView": true
    },
    {
        "name": "email_verified_at",
        "dbType": "datetime:nullable",
        "htmlType": "date",
        "validations": "nullable|nullable|nullable",
        "searchable": true,
        "fillable": true,
        "primary": false,
        "inForm": true,
        "inIndex": true,
        "inView": true
    },
    {
        "name": "password",
        "dbType": "string,255",
        "htmlType": "text",
        "validations": "required|string|max:255|string|max:255|string|max:255",
        "searchable": true,
        "fillable": true,
        "primary": false,
        "inForm": true,
        "inIndex": true,
        "inView": true
    },
    {
        "name": "remember_token",
        "dbType": "string,100:nullable",
        "htmlType": "text",
        "validations": "nullable|string|max:100|nullable|string|max:100|nullable|string|max:100",
        "searchable": true,
        "fillable": true,
        "primary": false,
        "inForm": true,
        "inIndex": true,
        "inView": true
    },
    {
        "name": "created_at",
        "dbType": "datetime:nullable",
        "htmlType": "date",
        "validations": "nullable|nullable|nullable",
        "searchable": false,
        "fillable": false,
        "primary": false,
        "inForm": false,
        "inIndex": false,
        "inView": false
    },
    {
        "name": "updated_at",
        "dbType": "datetime:nullable",
        "htmlType": "date",
        "validations": "nullable|nullable|nullable",
        "searchable": false,
        "fillable": false,
        "primary": false,
        "inForm": false,
        "inIndex": false,
        "inView": false
    },
    {
        "name": "hospital_id",
        "dbType": "bigInteger,false,true",
        "htmlType": null,
        "validations": "nullable|nullable|nullable",
        "searchable": true,
        "fillable": true,
        "primary": false,
        "inForm": true,
        "inIndex": true,
        "inView": true
    },
    {
        "name": "branch_id",
        "dbType": "bigInteger,false,true",
        "htmlType": null,
        "validations": "nullable|nullable|nullable",
        "searchable": true,
        "fillable": true,
        "primary": false,
        "inForm": true,
        "inIndex": true,
        "inView": true
    },
    {
        "name": "usertype_id",
        "dbType": "bigInteger,false,true",
        "htmlType": null,
        "validations": "nullable|nullable|nullable",
        "searchable": true,
        "fillable": true,
        "primary": false,
        "inForm": true,
        "inIndex": true,
        "inView": true
    },
    {
        "type": "relation",
        "relation": "mt1,Branch,branch_id"
    },
    {
        "type": "relation",
        "relation": "mt1,Hospital,hospital_id"
    },
    {
        "type": "relation",
        "relation": "mt1,Usertype,usertype_id"
    },
    {
        "type": "relation",
        "relation": "1tm,Session,cancelled_by"
    },
    {
        "type": "relation",
        "relation": "1tm,Session,completed_by"
    },
    {
        "type": "relation",
        "relation": "1tm,Session,started_by"
    },
    {
        "type": "relation",
        "relation": "1tm,UserHospital,user_id"
    },
    {
        "type": "relation",
        "relation": "1tm,UserUsergroup,user_id"
    }
]